st_agraph_symrzknr/__init__.py
st_agraph_symrzknr/frontend/build/asset-manifest.json
st_agraph_symrzknr/frontend/build/bootstrap.min.css
st_agraph_symrzknr/frontend/build/index.html
st_agraph_symrzknr/frontend/build/static/js/2.5ee34e29.chunk.js
st_agraph_symrzknr/frontend/build/static/js/2.5ee34e29.chunk.js.LICENSE.txt
st_agraph_symrzknr/frontend/build/static/js/2.5ee34e29.chunk.js.map
st_agraph_symrzknr/frontend/build/static/js/main.f2db5b75.chunk.js
st_agraph_symrzknr/frontend/build/static/js/main.f2db5b75.chunk.js.map
st_agraph_symrzknr/frontend/build/static/js/runtime-main.5caf0b1a.js
st_agraph_symrzknr/frontend/build/static/js/runtime-main.5caf0b1a.js.map
st_agraph_symrzknr-0.0.42.dist-info/LICENSE
st_agraph_symrzknr-0.0.42.dist-info/METADATA
st_agraph_symrzknr-0.0.42.dist-info/WHEEL
st_agraph_symrzknr-0.0.42.dist-info/top_level.txt
st_agraph_symrzknr-0.0.42.dist-info/RECORD
