Metadata-Version: 2.1
Name: st-agraph-symrzknr
Version: 0.0.42
Summary: Interactive Graph Vis for Streamlit, forked from original
Home-page: https://github.com/symrzknr/st-agraph-symrzknr
Author: symrzknr
Author-email: mrevuelta.deca@gmail.com
License: UNKNOWN
Platform: UNKNOWN
Requires-Python: >=3.6
Requires-Dist: streamlit (>=0.63)
Requires-Dist: networkx (>=2.5)
